substack/__init__.py
substack/auth.py
substack/client.py
substack/errors.py
substack/structures.py
substack/version.py
substack/api/__init__.py
substack/api/base.py
substack/api/posts.py
substack/api/publication.py
substack/api/user.py
substack/md_to_json/__init__.py
substack/md_to_json/inline_parser.py
substack/md_to_json/parsers.py
substack/md_to_json/structures.py
substack/utils/__init__.py
substack/utils/config.py
substack/utils/decorators.py
substack/utils/http.py
substack_python-0.1.0rc1.dist-info/METADATA
substack_python-0.1.0rc1.dist-info/WHEEL
substack_python-0.1.0rc1.dist-info/licenses/LICENSE
substack_python-0.1.0rc1.dist-info/RECORD
